ldaplogin/__init__.py
ldaplogin/login.py
ldaplogin/logout.py
ldaplogin/setup_credentials.py
ldaplogin_iitmandi-1.0.dist-info/METADATA
ldaplogin_iitmandi-1.0.dist-info/WHEEL
ldaplogin_iitmandi-1.0.dist-info/entry_points.txt
ldaplogin_iitmandi-1.0.dist-info/top_level.txt
ldaplogin_iitmandi-1.0.dist-info/RECORD
