Metadata-Version: 2.1
Name: ldaplogin-iitmandi
Version: 1.0
Summary: Quick login into the annoying LDAP
Home-page: https://github.com/nandan645/LDAP-Auto-Login
Author: Abhi Nandan
Author-email: nandan645@protonmail.com
Classifier: Programming Language :: Python :: 3
Classifier: License :: OSI Approved :: MIT License
Classifier: Operating System :: OS Independent
Requires-Dist: httpx
Requires-Dist: beautifulsoup4
Requires-Dist: keyring
